{
  "$description": "Korean EMR Domain Terminology for UbiCare Design System. Comprehensive glossary of terms used in Korean healthcare IT / EMR systems.",
  "$version": "1.0.0",
  "$lastUpdated": "2026-03-09",

  "modules": {
    "접수": { "korean": "접수", "english": "Registration", "description": "환자 내원 시 접수 및 환자 정보 등록 모듈" },
    "진료": { "korean": "진료", "english": "Consultation / Clinical", "description": "의사 진료 및 차트 기록 모듈" },
    "처방": { "korean": "처방", "english": "Prescription / Order", "description": "약품/검사/처치 처방 모듈" },
    "수납": { "korean": "수납", "english": "Payment / Checkout", "description": "진료비 수납 및 영수증 발급 모듈" },
    "보험청구": { "korean": "보험청구", "english": "Insurance Claims", "description": "건강보험 심사청구 및 EDI 전송 모듈" },
    "수탁검사": { "korean": "수탁검사", "english": "Consigned Tests", "description": "외부 검사기관 위탁 검사 모듈" },
    "예약": { "korean": "예약", "english": "Appointment", "description": "환자 예약 관리 모듈" },
    "CRM": { "korean": "CRM", "english": "Customer Relationship Management", "description": "환자 관계 관리 및 마케팅 모듈" },
    "서식": { "korean": "서식", "english": "Forms / Documents", "description": "제증명 및 의료문서 발급 모듈" },
    "기초자료": { "korean": "기초자료", "english": "Master Data", "description": "약품/상병/수가 등 기초 마스터 데이터 관리 모듈" },
    "시스템공통": { "korean": "시스템공통", "english": "System Common", "description": "전체 시스템 공통 설정 및 관리 모듈" }
  },

  "terminology": [

    {
      "id": "T001",
      "korean": "EMR",
      "koreanFull": "전자의무기록",
      "english": "Electronic Medical Record",
      "abbreviation": "EMR",
      "module": "시스템공통",
      "primaryUser": "전체",
      "definition": "환자 진료 시 발생하는 모든 의료정보를 전산으로 기록, 저장, 관리하는 시스템. 종이 차트를 대체하여 정보 접근성을 향상시키고 의료 오류를 줄이는 목적.",
      "relatedTerms": ["EHR", "OCS", "HIS"]
    },
    {
      "id": "T002",
      "korean": "EHR",
      "koreanFull": "전자건강기록",
      "english": "Electronic Health Record",
      "abbreviation": "EHR",
      "module": "시스템공통",
      "primaryUser": "전체",
      "definition": "EMR보다 넓은 개념으로, 여러 의료기관 간 공유 가능한 환자의 통합 건강 기록. 환자 중심의 기록 체계.",
      "relatedTerms": ["EMR", "PHR"]
    },
    {
      "id": "T003",
      "korean": "OCS",
      "koreanFull": "처방전달시스템",
      "english": "Order Communication System",
      "abbreviation": "OCS",
      "module": "처방",
      "primaryUser": "전체",
      "definition": "의사의 처방을 통신망을 통해 약국, 검사실, 간호 스테이션 등 각 해당 부서로 전달하는 시스템.",
      "relatedTerms": ["EMR", "CPOE"]
    },
    {
      "id": "T004",
      "korean": "HIS",
      "koreanFull": "병원정보시스템",
      "english": "Hospital Information System",
      "abbreviation": "HIS",
      "module": "시스템공통",
      "primaryUser": "전체",
      "definition": "병원의 의료, 행정, 재정, 법적 문제 등 운영의 모든 측면을 관리하는 포괄적 통합 정보 시스템.",
      "relatedTerms": ["EMR", "OCS", "PACS", "LIS"]
    },
    {
      "id": "T005",
      "korean": "PACS",
      "koreanFull": "의료영상저장전송시스템",
      "english": "Picture Archiving and Communication System",
      "abbreviation": "PACS",
      "module": "진료",
      "primaryUser": "의사",
      "definition": "X-ray, CT, MRI 등 의료영상을 디지털로 저장, 전송, 조회하는 시스템. 필름 없이 영상 확인 가능.",
      "relatedTerms": ["DICOM", "RIS"]
    },
    {
      "id": "T006",
      "korean": "LIS",
      "koreanFull": "진단검사정보시스템",
      "english": "Laboratory Information System",
      "abbreviation": "LIS",
      "module": "수탁검사",
      "primaryUser": "전체",
      "definition": "진단검사의학과에서 검체 접수, 검사 진행, 결과 보고를 관리하는 정보 시스템. EMR과 연동하여 검사 결과 자동 전송.",
      "relatedTerms": ["EMR", "수탁검사", "검체"]
    },
    {
      "id": "T007",
      "korean": "CPOE",
      "koreanFull": "전산화처방입력",
      "english": "Computerized Physician Order Entry",
      "abbreviation": "CPOE",
      "module": "처방",
      "primaryUser": "의사",
      "definition": "의사가 컴퓨터를 통해 직접 처방을 입력하는 시스템. DUR 점검과 연계하여 처방 안전성 확보.",
      "relatedTerms": ["OCS", "DUR"]
    },
    {
      "id": "T008",
      "korean": "PHR",
      "koreanFull": "개인건강기록",
      "english": "Personal Health Record",
      "abbreviation": "PHR",
      "module": "시스템공통",
      "primaryUser": "전체",
      "definition": "환자 본인이 자신의 건강정보를 관리할 수 있는 시스템. 모바일 앱 등으로 건강 데이터 열람.",
      "relatedTerms": ["EHR", "EMR"]
    },

    {
      "id": "T010",
      "korean": "접수",
      "koreanFull": "접수",
      "english": "Registration / Check-in",
      "abbreviation": null,
      "module": "접수",
      "primaryUser": "원무과",
      "definition": "환자가 병원에 내원하여 진료를 받기 위해 등록하는 과정. 환자 정보 확인, 보험 자격 조회, 진료과 배정 등을 수행.",
      "relatedTerms": ["환자등록", "보험자격조회", "초진", "재진"]
    },
    {
      "id": "T011",
      "korean": "환자등록",
      "koreanFull": "환자등록",
      "english": "Patient Registration",
      "abbreviation": null,
      "module": "접수",
      "primaryUser": "원무과",
      "definition": "신규 환자의 기본 정보(성명, 주민등록번호, 연락처, 주소, 보험 정보 등)를 시스템에 등록하는 과정.",
      "relatedTerms": ["차트번호", "환자번호", "접수"]
    },
    {
      "id": "T012",
      "korean": "차트번호",
      "koreanFull": "차트번호",
      "english": "Chart Number",
      "abbreviation": null,
      "module": "접수",
      "primaryUser": "원무과",
      "definition": "환자 등록 시 자동 부여되는 고유 식별 번호. 해당 의료기관 내에서 환자를 고유하게 식별하는 데 사용.",
      "relatedTerms": ["환자번호", "환자등록"]
    },
    {
      "id": "T013",
      "korean": "초진",
      "koreanFull": "초진",
      "english": "First Visit / Initial Consultation",
      "abbreviation": null,
      "module": "접수",
      "primaryUser": "원무과",
      "definition": "해당 의료기관에 처음 내원하거나, 치료 완료 후 90일 이상 경과 후 다시 내원하는 경우. 초진료가 재진료보다 높음.",
      "relatedTerms": ["재진", "진찰료"]
    },
    {
      "id": "T014",
      "korean": "재진",
      "koreanFull": "재진",
      "english": "Follow-up Visit / Return Visit",
      "abbreviation": null,
      "module": "접수",
      "primaryUser": "원무과",
      "definition": "동일 상병으로 치료 완료 이후 30일 이내에 다시 내원하는 경우. 초진에 비해 진찰료가 낮음.",
      "relatedTerms": ["초진", "진찰료"]
    },
    {
      "id": "T015",
      "korean": "보험자격조회",
      "koreanFull": "보험자격조회",
      "english": "Insurance Eligibility Verification",
      "abbreviation": null,
      "module": "접수",
      "primaryUser": "원무과",
      "definition": "환자의 건강보험 자격, 보험 유형(건강보험/의료급여/산재/자보차 등), 산정특례 적용 여부 등을 실시간 조회.",
      "relatedTerms": ["건강보험", "의료급여", "산재보험", "자동차보험"]
    },
    {
      "id": "T016",
      "korean": "대기환자",
      "koreanFull": "대기환자",
      "english": "Waiting Patient",
      "abbreviation": null,
      "module": "접수",
      "primaryUser": "원무과",
      "definition": "접수를 완료하고 진료실 앞에서 순서를 기다리고 있는 환자. EMR에서 대기 목록으로 관리.",
      "relatedTerms": ["접수", "진료대기"]
    },
    {
      "id": "T017",
      "korean": "진료대기",
      "koreanFull": "진료대기",
      "english": "Waiting for Consultation",
      "abbreviation": null,
      "module": "접수",
      "primaryUser": "원무과",
      "definition": "접수 완료 후 의사 진료를 기다리는 상태. 대기 현황판이나 키오스크를 통해 환자에게 대기 순서 안내.",
      "relatedTerms": ["대기환자", "접수"]
    },

    {
      "id": "T020",
      "korean": "진료",
      "koreanFull": "진료",
      "english": "Consultation / Medical Examination",
      "abbreviation": null,
      "module": "진료",
      "primaryUser": "의사",
      "definition": "의사가 환자를 진찰하고 질병을 진단하며 치료 방침을 결정하는 전체 과정.",
      "relatedTerms": ["진찰", "처방", "SOAP"]
    },
    {
      "id": "T021",
      "korean": "차트",
      "koreanFull": "차트 / 진료기록",
      "english": "Chart / Medical Record",
      "abbreviation": null,
      "module": "진료",
      "primaryUser": "의사",
      "definition": "환자의 진료 내용, 검사 결과, 처방 이력 등을 기록하는 의무 문서. EMR에서 전자적으로 작성 및 관리.",
      "relatedTerms": ["EMR", "진료노트", "SOAP"]
    },
    {
      "id": "T022",
      "korean": "SOAP",
      "koreanFull": "SOAP 노트",
      "english": "Subjective, Objective, Assessment, Plan",
      "abbreviation": "SOAP",
      "module": "진료",
      "primaryUser": "의사",
      "definition": "진료 기록 작성의 표준 형식. S(주관적 소견: 환자 호소), O(객관적 소견: 검사 결과), A(평가: 진단), P(계획: 치료 방침).",
      "relatedTerms": ["진료노트", "차트"]
    },
    {
      "id": "T023",
      "korean": "주소증",
      "koreanFull": "주소증",
      "english": "Chief Complaint",
      "abbreviation": "CC / C.C.",
      "module": "진료",
      "primaryUser": "의사",
      "definition": "환자가 병원을 방문하게 된 주된 증상이나 이유. 진료기록에서 가장 먼저 기록되는 항목.",
      "relatedTerms": ["현병력", "SOAP"]
    },
    {
      "id": "T024",
      "korean": "현병력",
      "koreanFull": "현병력",
      "english": "Present Illness / History of Present Illness",
      "abbreviation": "PI / HPI",
      "module": "진료",
      "primaryUser": "의사",
      "definition": "현재 앓고 있는 질환의 발병 시기, 경과, 양상 등을 상세히 기록한 병력. 주소증의 시간적 경과를 기술.",
      "relatedTerms": ["주소증", "과거력"]
    },
    {
      "id": "T025",
      "korean": "과거력",
      "koreanFull": "과거력",
      "english": "Past Medical History",
      "abbreviation": "PMH",
      "module": "진료",
      "primaryUser": "의사",
      "definition": "환자가 과거에 앓았던 질병, 수술, 입원 이력 등. 현재 질환의 진단 및 치료 계획 수립에 참고.",
      "relatedTerms": ["현병력", "가족력"]
    },
    {
      "id": "T026",
      "korean": "가족력",
      "koreanFull": "가족력",
      "english": "Family History",
      "abbreviation": "FH / FHx",
      "module": "진료",
      "primaryUser": "의사",
      "definition": "혈연관계에 있는 가족 구성원의 질병 이력. 유전적 소인이 있는 질환의 진단에 참고.",
      "relatedTerms": ["과거력", "사회력"]
    },
    {
      "id": "T027",
      "korean": "사회력",
      "koreanFull": "사회력",
      "english": "Social History",
      "abbreviation": "SH / SHx",
      "module": "진료",
      "primaryUser": "의사",
      "definition": "환자의 직업, 음주, 흡연, 운동 등 생활습관 및 사회적 배경 정보.",
      "relatedTerms": ["과거력", "가족력"]
    },
    {
      "id": "T028",
      "korean": "이학적검사",
      "koreanFull": "이학적검사 / 신체검사",
      "english": "Physical Examination",
      "abbreviation": "PE / P/E",
      "module": "진료",
      "primaryUser": "의사",
      "definition": "시진, 촉진, 청진, 타진 등 의사가 직접 환자의 신체를 검사하여 소견을 확인하는 행위.",
      "relatedTerms": ["활력징후", "SOAP"]
    },
    {
      "id": "T029",
      "korean": "활력징후",
      "koreanFull": "활력징후 / 바이탈사인",
      "english": "Vital Signs",
      "abbreviation": "V/S",
      "module": "진료",
      "primaryUser": "간호사",
      "definition": "체온(BT), 맥박(PR), 호흡수(RR), 혈압(BP)의 4가지 기본 생체 징후. 환자의 생명 유지 상태를 나타내는 기본 지표.",
      "relatedTerms": ["체온", "혈압", "맥박", "호흡"]
    },
    {
      "id": "T030",
      "korean": "혈압",
      "koreanFull": "혈압",
      "english": "Blood Pressure",
      "abbreviation": "BP",
      "module": "진료",
      "primaryUser": "간호사",
      "definition": "동맥 혈관벽에 대한 혈액의 압력. 수축기혈압(SBP)/이완기혈압(DBP)으로 표기. 단위: mmHg.",
      "relatedTerms": ["활력징후"]
    },
    {
      "id": "T031",
      "korean": "맥박",
      "koreanFull": "맥박",
      "english": "Pulse Rate",
      "abbreviation": "PR",
      "module": "진료",
      "primaryUser": "간호사",
      "definition": "1분간 동맥에서 느껴지는 박동 수. 정상 성인: 60~100회/분.",
      "relatedTerms": ["활력징후"]
    },
    {
      "id": "T032",
      "korean": "체온",
      "koreanFull": "체온",
      "english": "Body Temperature",
      "abbreviation": "BT",
      "module": "진료",
      "primaryUser": "간호사",
      "definition": "인체의 온도. 구강, 고막, 액와 등으로 측정. 정상: 36.5~37.5도C.",
      "relatedTerms": ["활력징후"]
    },
    {
      "id": "T033",
      "korean": "호흡수",
      "koreanFull": "호흡수",
      "english": "Respiratory Rate",
      "abbreviation": "RR",
      "module": "진료",
      "primaryUser": "간호사",
      "definition": "1분간 호흡하는 횟수. 정상 성인: 12~20회/분.",
      "relatedTerms": ["활력징후"]
    },
    {
      "id": "T034",
      "korean": "신장",
      "koreanFull": "신장 / 키",
      "english": "Height",
      "abbreviation": "Ht",
      "module": "진료",
      "primaryUser": "간호사",
      "definition": "환자의 키. 단위: cm. BMI 계산 등에 사용.",
      "relatedTerms": ["체중", "BMI"]
    },
    {
      "id": "T035",
      "korean": "체중",
      "koreanFull": "체중",
      "english": "Weight",
      "abbreviation": "Wt / BW",
      "module": "진료",
      "primaryUser": "간호사",
      "definition": "환자의 몸무게. 단위: kg. 약물 용량 산정, BMI 계산 등에 사용.",
      "relatedTerms": ["신장", "BMI"]
    },
    {
      "id": "T036",
      "korean": "BMI",
      "koreanFull": "체질량지수",
      "english": "Body Mass Index",
      "abbreviation": "BMI",
      "module": "진료",
      "primaryUser": "의사",
      "definition": "체중(kg)을 신장(m)의 제곱으로 나눈 값. 비만도 판정 지표.",
      "relatedTerms": ["신장", "체중"]
    },
    {
      "id": "T037",
      "korean": "상병",
      "koreanFull": "상병 / 진단명",
      "english": "Diagnosis / Disease",
      "abbreviation": null,
      "module": "진료",
      "primaryUser": "의사",
      "definition": "환자에게 내려진 질병 진단. KCD 코드로 분류되며 보험 청구의 기본 단위.",
      "relatedTerms": ["KCD", "상병코드", "주상병", "부상병"]
    },
    {
      "id": "T038",
      "korean": "주상병",
      "koreanFull": "주상병",
      "english": "Principal Diagnosis",
      "abbreviation": null,
      "module": "진료",
      "primaryUser": "의사",
      "definition": "진료의 주된 원인이 되는 가장 중요한 진단. 보험 청구 시 반드시 1개 이상 입력해야 함.",
      "relatedTerms": ["부상병", "상병코드"]
    },
    {
      "id": "T039",
      "korean": "부상병",
      "koreanFull": "부상병",
      "english": "Secondary Diagnosis",
      "abbreviation": null,
      "module": "진료",
      "primaryUser": "의사",
      "definition": "주상병 외에 추가로 진단된 질병. 주상병과 함께 기록하여 환자 상태를 보다 정확히 반영.",
      "relatedTerms": ["주상병", "상병코드"]
    },
    {
      "id": "T040",
      "korean": "의증",
      "koreanFull": "의증 / 의심진단",
      "english": "Suspected Diagnosis / Rule Out",
      "abbreviation": "R/O",
      "module": "진료",
      "primaryUser": "의사",
      "definition": "확정 진단 전 의심되는 진단명. 상병코드 앞에 V(Suspected)를 붙여 표시. R/O(Rule Out)로도 표현.",
      "relatedTerms": ["상병", "확정진단"]
    },
    {
      "id": "T041",
      "korean": "진료노트",
      "koreanFull": "진료노트",
      "english": "Progress Note / Clinical Note",
      "abbreviation": null,
      "module": "진료",
      "primaryUser": "의사",
      "definition": "진료 시 작성하는 경과 기록. SOAP 형식 또는 자유 형식으로 작성. 진료의 근거와 판단을 문서화.",
      "relatedTerms": ["SOAP", "차트"]
    },
    {
      "id": "T042",
      "korean": "진료템플릿",
      "koreanFull": "진료템플릿",
      "english": "Clinical Template",
      "abbreviation": null,
      "module": "진료",
      "primaryUser": "의사",
      "definition": "질환별 또는 진료 유형별 미리 정의된 차트 양식. 반복적인 기록 작성의 효율성을 높이기 위한 기능.",
      "relatedTerms": ["상용구", "처방세트"]
    },
    {
      "id": "T043",
      "korean": "상용구",
      "koreanFull": "상용구",
      "english": "Text Snippet / Boilerplate",
      "abbreviation": null,
      "module": "진료",
      "primaryUser": "의사",
      "definition": "자주 사용되는 문구를 미리 저장해두고 단축키나 코드로 빠르게 입력하는 기능.",
      "relatedTerms": ["진료템플릿", "처방세트"]
    },

    {
      "id": "T050",
      "korean": "처방",
      "koreanFull": "처방",
      "english": "Prescription / Order",
      "abbreviation": "Rx",
      "module": "처방",
      "primaryUser": "의사",
      "definition": "의사가 환자에게 약품, 검사, 처치 등을 지시하는 행위. EMR에서 전산으로 입력 및 전달.",
      "relatedTerms": ["원외처방", "원내처방", "처방전"]
    },
    {
      "id": "T051",
      "korean": "원외처방",
      "koreanFull": "원외처방",
      "english": "Out-of-Hospital Prescription",
      "abbreviation": null,
      "module": "처방",
      "primaryUser": "의사",
      "definition": "의원에서 처방전을 발행하여 외부 약국에서 조제하는 처방. 의약분업 이후 일반적인 처방 형태.",
      "relatedTerms": ["원내처방", "처방전", "조제"]
    },
    {
      "id": "T052",
      "korean": "원내처방",
      "koreanFull": "원내처방",
      "english": "In-Hospital Prescription / Dispensing",
      "abbreviation": null,
      "module": "처방",
      "primaryUser": "의사",
      "definition": "의료기관 내에서 직접 약품을 조제하여 투약하는 처방. 주사제, 외용제, 응급약 등에 적용.",
      "relatedTerms": ["원외처방", "투약"]
    },
    {
      "id": "T053",
      "korean": "처방전",
      "koreanFull": "처방전",
      "english": "Prescription Form",
      "abbreviation": null,
      "module": "처방",
      "primaryUser": "의사",
      "definition": "의사가 작성하여 환자에게 발급하는 약품 처방 문서. 약품명, 용량, 용법, 투약일수 등이 기재됨.",
      "relatedTerms": ["원외처방", "조제"]
    },
    {
      "id": "T054",
      "korean": "용법",
      "koreanFull": "용법 / 투여방법",
      "english": "Dosage Instructions / Administration Method",
      "abbreviation": null,
      "module": "처방",
      "primaryUser": "의사",
      "definition": "약품의 복용 방법 및 시기. 예: 식후 30분, 취침 전, 1일 3회 등.",
      "relatedTerms": ["용량", "일투", "일수"]
    },
    {
      "id": "T055",
      "korean": "용량",
      "koreanFull": "용량 / 투여량",
      "english": "Dosage / Dose",
      "abbreviation": null,
      "module": "처방",
      "primaryUser": "의사",
      "definition": "한 번에 투여하는 약품의 양. 단위: mg, ml, 정(tablet), 캡슐(capsule) 등.",
      "relatedTerms": ["용법", "1회투약량"]
    },
    {
      "id": "T056",
      "korean": "일투",
      "koreanFull": "1일투여횟수",
      "english": "Daily Frequency / Times Per Day",
      "abbreviation": null,
      "module": "처방",
      "primaryUser": "의사",
      "definition": "하루에 약을 복용하는 횟수. 예: 1일 1회, 1일 2회, 1일 3회.",
      "relatedTerms": ["용법", "일수", "1회투약량"]
    },
    {
      "id": "T057",
      "korean": "일수",
      "koreanFull": "투약일수",
      "english": "Days of Medication / Duration",
      "abbreviation": null,
      "module": "처방",
      "primaryUser": "의사",
      "definition": "약을 복용하는 총 일수. 보험 청구 시 투약일수에 따라 약제비 산정.",
      "relatedTerms": ["일투", "총투여량"]
    },
    {
      "id": "T058",
      "korean": "1회투약량",
      "koreanFull": "1회투약량",
      "english": "Single Dose Amount",
      "abbreviation": null,
      "module": "처방",
      "primaryUser": "의사",
      "definition": "1회에 투여하는 약품의 양. 처방전의 필수 기재 항목.",
      "relatedTerms": ["용량", "일투"]
    },
    {
      "id": "T059",
      "korean": "처방세트",
      "koreanFull": "처방세트 / 오더세트",
      "english": "Order Set / Prescription Set",
      "abbreviation": null,
      "module": "처방",
      "primaryUser": "의사",
      "definition": "자주 사용하는 약품/검사/처치를 묶어 저장해둔 것. 한 번에 여러 항목을 일괄 처방할 수 있어 효율적.",
      "relatedTerms": ["즐겨찾기", "진료템플릿"]
    },
    {
      "id": "T060",
      "korean": "즐겨찾기",
      "koreanFull": "즐겨찾기",
      "english": "Favorites / Quick Access",
      "abbreviation": null,
      "module": "처방",
      "primaryUser": "의사",
      "definition": "자주 사용하는 약품, 검사, 상병 등을 즐겨찾기로 등록하여 빠르게 접근하는 기능.",
      "relatedTerms": ["처방세트"]
    },
    {
      "id": "T061",
      "korean": "DUR",
      "koreanFull": "의약품안전사용서비스",
      "english": "Drug Utilization Review",
      "abbreviation": "DUR",
      "module": "처방",
      "primaryUser": "의사",
      "definition": "건강보험심사평가원에서 제공하는 의약품 안전성 실시간 점검 서비스. 처방/조제 시 금기 사항 등을 자동 경고.",
      "relatedTerms": ["병용금기", "연령금기", "임부금기"]
    },
    {
      "id": "T062",
      "korean": "병용금기",
      "koreanFull": "병용금기",
      "english": "Drug-Drug Interaction Contraindication",
      "abbreviation": null,
      "module": "처방",
      "primaryUser": "의사",
      "definition": "함께 복용하면 안 되는 약물 조합. DUR 점검에서 실시간으로 경고 제공.",
      "relatedTerms": ["DUR", "연령금기", "임부금기"]
    },
    {
      "id": "T063",
      "korean": "연령금기",
      "koreanFull": "연령금기",
      "english": "Age-Related Contraindication",
      "abbreviation": null,
      "module": "처방",
      "primaryUser": "의사",
      "definition": "특정 연령대에서 사용이 금지된 약물. 소아/고령자 등에 대한 안전성 점검.",
      "relatedTerms": ["DUR", "병용금기"]
    },
    {
      "id": "T064",
      "korean": "임부금기",
      "koreanFull": "임부금기",
      "english": "Pregnancy Contraindication",
      "abbreviation": null,
      "module": "처방",
      "primaryUser": "의사",
      "definition": "임산부에게 사용이 금지되거나 주의가 필요한 약물. DUR 점검 항목.",
      "relatedTerms": ["DUR", "병용금기"]
    },
    {
      "id": "T065",
      "korean": "효능군중복",
      "koreanFull": "성분/효능군 중복",
      "english": "Therapeutic Duplication",
      "abbreviation": null,
      "module": "처방",
      "primaryUser": "의사",
      "definition": "같은 효능을 가진 약물이 중복 처방되는 경우. DUR에서 점검하여 경고.",
      "relatedTerms": ["DUR", "병용금기"]
    },
    {
      "id": "T066",
      "korean": "조제",
      "koreanFull": "조제",
      "english": "Dispensing / Compounding",
      "abbreviation": null,
      "module": "처방",
      "primaryUser": "전체",
      "definition": "의사의 처방전에 따라 약사가 약품을 배합하여 환자에게 제공하는 행위.",
      "relatedTerms": ["처방전", "조제료"]
    },

    {
      "id": "T070",
      "korean": "수납",
      "koreanFull": "수납",
      "english": "Payment / Checkout / Billing",
      "abbreviation": null,
      "module": "수납",
      "primaryUser": "원무과",
      "definition": "진료 후 환자가 진료비를 납부하는 과정. 본인부담금 계산 및 영수증 발급.",
      "relatedTerms": ["본인부담금", "영수증", "미수금"]
    },
    {
      "id": "T071",
      "korean": "본인부담금",
      "koreanFull": "본인부담금",
      "english": "Patient Copayment / Out-of-Pocket Cost",
      "abbreviation": null,
      "module": "수납",
      "primaryUser": "원무과",
      "definition": "전체 진료비 중 환자가 직접 부담하는 금액. 보험 유형과 진료 내용에 따라 부담률이 다름.",
      "relatedTerms": ["본인부담률", "요양급여", "비급여"]
    },
    {
      "id": "T072",
      "korean": "본인부담률",
      "koreanFull": "본인부담률",
      "english": "Copayment Rate",
      "abbreviation": null,
      "module": "수납",
      "primaryUser": "원무과",
      "definition": "진료비 총액 중 환자가 부담하는 비율. 의원 외래: 30%, 병원 외래: 40%, 종합병원 외래: 50% 등.",
      "relatedTerms": ["본인부담금", "요양급여"]
    },
    {
      "id": "T073",
      "korean": "미수금",
      "koreanFull": "미수금",
      "english": "Outstanding Balance / Unpaid Amount",
      "abbreviation": null,
      "module": "수납",
      "primaryUser": "원무과",
      "definition": "환자가 아직 납부하지 않은 진료비 잔액. 수납 모듈에서 미수 관리 기능으로 추적.",
      "relatedTerms": ["수납", "수납취소"]
    },
    {
      "id": "T074",
      "korean": "영수증",
      "koreanFull": "영수증",
      "english": "Receipt",
      "abbreviation": null,
      "module": "수납",
      "primaryUser": "원무과",
      "definition": "진료비 납부 후 발급되는 증빙 문서. 실손보험 청구 등에 사용.",
      "relatedTerms": ["진료비세부내역서", "수납"]
    },
    {
      "id": "T075",
      "korean": "진료비세부내역서",
      "koreanFull": "진료비세부내역서",
      "english": "Detailed Medical Bill Statement",
      "abbreviation": null,
      "module": "수납",
      "primaryUser": "원무과",
      "definition": "진찰료, 검사료, 투약료, 처치료 등 진료비 항목별 상세 내역을 기재한 문서.",
      "relatedTerms": ["영수증", "진찰료"]
    },
    {
      "id": "T076",
      "korean": "수납취소",
      "koreanFull": "수납취소",
      "english": "Payment Cancellation / Refund",
      "abbreviation": null,
      "module": "수납",
      "primaryUser": "원무과",
      "definition": "이미 완료된 수납을 취소하고 환불 처리하는 기능.",
      "relatedTerms": ["수납", "미수금"]
    },

    {
      "id": "T080",
      "korean": "급여",
      "koreanFull": "급여 / 요양급여",
      "english": "Covered Service / Insurance Benefit",
      "abbreviation": null,
      "module": "보험청구",
      "primaryUser": "원무과",
      "definition": "국민건강보험에서 비용을 부담(지급)하는 의료 서비스. 환자는 본인부담률에 해당하는 일부만 부담.",
      "relatedTerms": ["비급여", "선별급여", "본인부담금"]
    },
    {
      "id": "T081",
      "korean": "비급여",
      "koreanFull": "비급여",
      "english": "Non-Covered Service / Non-Reimbursable",
      "abbreviation": null,
      "module": "보험청구",
      "primaryUser": "원무과",
      "definition": "건강보험이 적용되지 않아 환자가 전액 부담하는 의료 서비스. 예: 미용, 예방접종, 건강검진 등.",
      "relatedTerms": ["급여", "선별급여", "전액본인부담"]
    },
    {
      "id": "T082",
      "korean": "선별급여",
      "koreanFull": "선별급여",
      "english": "Selective Benefit / Partially Covered",
      "abbreviation": null,
      "module": "보험청구",
      "primaryUser": "원무과",
      "definition": "급여와 비급여의 중간 단계. 환자 본인부담률이 50~90%로 높지만 보험 일부 적용되는 항목.",
      "relatedTerms": ["급여", "비급여", "예비급여"]
    },
    {
      "id": "T083",
      "korean": "전액본인부담",
      "koreanFull": "전액본인부담",
      "english": "Full Patient Responsibility / 100% Copay",
      "abbreviation": null,
      "module": "보험청구",
      "primaryUser": "원무과",
      "definition": "급여 항목이지만 본인부담률이 100%인 항목. 업무상 질병, 경증질환 상급종합병원 외래 등.",
      "relatedTerms": ["급여", "비급여"]
    },
    {
      "id": "T084",
      "korean": "수가",
      "koreanFull": "수가 / 의료수가",
      "english": "Medical Fee / Fee Schedule",
      "abbreviation": null,
      "module": "보험청구",
      "primaryUser": "원무과",
      "definition": "의료 행위에 대해 정해진 가격. 건강보험심사평가원이 고시하며 행위별, 약가, 재료대로 구분.",
      "relatedTerms": ["행위수가", "약가", "재료대"]
    },
    {
      "id": "T085",
      "korean": "행위수가",
      "koreanFull": "행위수가",
      "english": "Fee-for-Service / Procedure Fee",
      "abbreviation": null,
      "module": "보험청구",
      "primaryUser": "원무과",
      "definition": "의료 행위(진찰, 검사, 처치, 수술 등)에 대해 건별로 책정된 가격.",
      "relatedTerms": ["수가", "행위코드"]
    },
    {
      "id": "T086",
      "korean": "행위코드",
      "koreanFull": "행위코드 / 수가코드",
      "english": "Procedure Code / Fee Code",
      "abbreviation": null,
      "module": "보험청구",
      "primaryUser": "원무과",
      "definition": "각 의료 행위에 부여된 고유 코드. HIRA에서 관리하며 보험 청구 시 사용. 예: 진찰료 AA, 검사 C 등.",
      "relatedTerms": ["수가", "EDI코드"]
    },
    {
      "id": "T087",
      "korean": "약가",
      "koreanFull": "약가 / 약제비",
      "english": "Drug Price / Drug Cost",
      "abbreviation": null,
      "module": "보험청구",
      "primaryUser": "원무과",
      "definition": "건강보험에서 인정하는 약품의 가격. 약품코드별로 상한금액이 고시됨.",
      "relatedTerms": ["약품코드", "수가"]
    },
    {
      "id": "T088",
      "korean": "약품코드",
      "koreanFull": "약품코드 / 약가코드",
      "english": "Drug Code / Drug Price Code",
      "abbreviation": null,
      "module": "보험청구",
      "primaryUser": "원무과",
      "definition": "건강보험심사평가원에서 각 약품에 부여한 고유 코드. EDI 청구 시 사용되는 9자리 코드.",
      "relatedTerms": ["약가", "EDI코드", "ATC코드"]
    },
    {
      "id": "T089",
      "korean": "재료대",
      "koreanFull": "재료대 / 치료재료",
      "english": "Material Cost / Medical Supplies",
      "abbreviation": null,
      "module": "보험청구",
      "primaryUser": "원무과",
      "definition": "치료에 사용되는 재료(거즈, 카테터, 임플란트 등)의 비용. 별도 수가코드로 청구.",
      "relatedTerms": ["수가", "행위코드"]
    },
    {
      "id": "T090",
      "korean": "심사청구",
      "koreanFull": "심사청구",
      "english": "Claim Submission / Review Request",
      "abbreviation": null,
      "module": "보험청구",
      "primaryUser": "원무과",
      "definition": "의료기관이 진료비를 건강보험심사평가원(HIRA)에 제출하여 심사를 받고 지급을 요청하는 과정.",
      "relatedTerms": ["EDI", "명세서", "삭감"]
    },
    {
      "id": "T091",
      "korean": "EDI",
      "koreanFull": "전자문서교환",
      "english": "Electronic Data Interchange",
      "abbreviation": "EDI",
      "module": "보험청구",
      "primaryUser": "원무과",
      "definition": "의료기관과 건강보험심사평가원/국민건강보험공단 간 전자적으로 문서를 교환하는 시스템. 청구, 심사결과, 각종 신고서류 전송.",
      "relatedTerms": ["심사청구", "HIRA", "NHIS"]
    },
    {
      "id": "T092",
      "korean": "명세서",
      "koreanFull": "요양급여비용 명세서",
      "english": "Claim Form / Benefit Cost Statement",
      "abbreviation": null,
      "module": "보험청구",
      "primaryUser": "원무과",
      "definition": "보험 청구 시 제출하는 진료 내역 상세 문서. 환자 정보, 상병, 행위, 약품, 재료 등 모든 진료 내역을 기재.",
      "relatedTerms": ["심사청구", "특정내역"]
    },
    {
      "id": "T093",
      "korean": "삭감",
      "koreanFull": "삭감 / 조정",
      "english": "Claim Reduction / Adjustment / Denial",
      "abbreviation": null,
      "module": "보험청구",
      "primaryUser": "원무과",
      "definition": "HIRA 심사 결과 인정되지 않아 청구 금액이 감액되는 것. 착오청구, 과잉청구, 기준 미충족 등이 원인.",
      "relatedTerms": ["심사청구", "이의신청"]
    },
    {
      "id": "T094",
      "korean": "이의신청",
      "koreanFull": "이의신청",
      "english": "Appeal / Objection",
      "abbreviation": null,
      "module": "보험청구",
      "primaryUser": "원무과",
      "definition": "삭감된 청구 내역에 대해 의료기관이 재심사를 요청하는 절차. 처분을 안 날로부터 90일 이내 제출.",
      "relatedTerms": ["삭감", "심사청구"]
    },
    {
      "id": "T095",
      "korean": "산정특례",
      "koreanFull": "본인일부부담금 산정특례",
      "english": "Copayment Reduction Special Case",
      "abbreviation": null,
      "module": "보험청구",
      "primaryUser": "원무과",
      "definition": "암, 희귀질환, 중증난치질환 등 고액 진료비가 필요한 환자의 본인부담률을 5~10%로 경감하는 제도.",
      "relatedTerms": ["본인부담금", "본인부담률"]
    },
    {
      "id": "T096",
      "korean": "특정내역",
      "koreanFull": "특정내역",
      "english": "Special Notes / Specific Details",
      "abbreviation": null,
      "module": "보험청구",
      "primaryUser": "원무과",
      "definition": "청구 명세서에 추가 기재하는 상세 사유. 심사 시 삭감을 방지하기 위해 의학적 사유를 설명하는 란.",
      "relatedTerms": ["명세서", "심사청구"]
    },
    {
      "id": "T097",
      "korean": "심사결과통보서",
      "koreanFull": "심사결과통보서",
      "english": "Claim Review Result Notification",
      "abbreviation": null,
      "module": "보험청구",
      "primaryUser": "원무과",
      "definition": "HIRA에서 청구 심사 완료 후 결과를 의료기관에 통보하는 문서. 인정/삭감 내역이 기재됨.",
      "relatedTerms": ["심사청구", "삭감", "EDI"]
    },
    {
      "id": "T098",
      "korean": "청구파일",
      "koreanFull": "청구파일",
      "english": "Claim File",
      "abbreviation": null,
      "module": "보험청구",
      "primaryUser": "원무과",
      "definition": "EDI를 통해 HIRA에 전송하는 보험 청구 데이터 파일. 명세서 내용을 전자 형태로 변환한 것.",
      "relatedTerms": ["EDI", "심사청구"]
    },
    {
      "id": "T099",
      "korean": "진찰료",
      "koreanFull": "진찰료",
      "english": "Consultation Fee",
      "abbreviation": null,
      "module": "보험청구",
      "primaryUser": "원무과",
      "definition": "의사가 환자를 진찰하는 행위에 대한 수가. 초진료/재진료로 구분되며 의료기관 종별로 금액 상이.",
      "relatedTerms": ["초진", "재진", "수가"]
    },
    {
      "id": "T100",
      "korean": "투약료",
      "koreanFull": "투약료",
      "english": "Medication Fee / Drug Administration Fee",
      "abbreviation": null,
      "module": "보험청구",
      "primaryUser": "원무과",
      "definition": "약품을 투여하는 행위에 대한 수가. 원내처방 시 약제비와 함께 청구.",
      "relatedTerms": ["주사료", "처방료", "약가"]
    },
    {
      "id": "T101",
      "korean": "주사료",
      "koreanFull": "주사료",
      "english": "Injection Fee",
      "abbreviation": null,
      "module": "보험청구",
      "primaryUser": "원무과",
      "definition": "주사 투여 행위에 대한 수가. 근육주사, 정맥주사, 피하주사 등 투여 경로에 따라 구분.",
      "relatedTerms": ["투약료", "수가"]
    },
    {
      "id": "T102",
      "korean": "처방료",
      "koreanFull": "처방료",
      "english": "Prescription Fee",
      "abbreviation": null,
      "module": "보험청구",
      "primaryUser": "원무과",
      "definition": "원외처방전을 발행하는 행위에 대한 수가. 의약분업에 따라 처방전 발행 시 청구.",
      "relatedTerms": ["조제료", "원외처방"]
    },
    {
      "id": "T103",
      "korean": "조제료",
      "koreanFull": "조제료",
      "english": "Dispensing Fee",
      "abbreviation": null,
      "module": "보험청구",
      "primaryUser": "원무과",
      "definition": "약사가 처방전에 따라 약을 조제하는 행위에 대한 수가. 약품 품목수에 따라 차등 적용.",
      "relatedTerms": ["처방료", "조제"]
    },
    {
      "id": "T104",
      "korean": "검사료",
      "koreanFull": "검사료",
      "english": "Test Fee / Laboratory Fee",
      "abbreviation": null,
      "module": "보험청구",
      "primaryUser": "원무과",
      "definition": "혈액검사, 소변검사 등 진단검사에 대한 수가.",
      "relatedTerms": ["수가", "영상진단료"]
    },
    {
      "id": "T105",
      "korean": "영상진단료",
      "koreanFull": "영상진단료",
      "english": "Imaging Diagnostic Fee",
      "abbreviation": null,
      "module": "보험청구",
      "primaryUser": "원무과",
      "definition": "X-ray, CT, MRI, 초음파 등 영상 검사에 대한 수가.",
      "relatedTerms": ["검사료", "PACS"]
    },
    {
      "id": "T106",
      "korean": "처치료",
      "koreanFull": "처치료",
      "english": "Treatment/Procedure Fee",
      "abbreviation": null,
      "module": "보험청구",
      "primaryUser": "원무과",
      "definition": "봉합, 배농, 부목 고정 등 의료 처치 행위에 대한 수가.",
      "relatedTerms": ["수가", "행위코드"]
    },
    {
      "id": "T107",
      "korean": "입원료",
      "koreanFull": "입원료",
      "english": "Hospitalization Fee / Inpatient Fee",
      "abbreviation": null,
      "module": "보험청구",
      "primaryUser": "원무과",
      "definition": "입원 환자에게 부과되는 기본 수가. 병실 유형(일반, 상급)에 따라 금액 상이.",
      "relatedTerms": ["수가", "외래"]
    },
    {
      "id": "T108",
      "korean": "야간가산",
      "koreanFull": "야간/휴일 가산",
      "english": "Night/Holiday Surcharge",
      "abbreviation": null,
      "module": "보험청구",
      "primaryUser": "원무과",
      "definition": "야간(18시~22시 30%), 심야(22시~06시 50%), 공휴일(30%)에 진료 시 기본 수가에 추가되는 가산금.",
      "relatedTerms": ["수가", "진찰료"]
    },

    {
      "id": "T110",
      "korean": "보험유형",
      "koreanFull": "보험유형",
      "english": "Insurance Type",
      "abbreviation": null,
      "module": "접수",
      "primaryUser": "원무과",
      "definition": "환자의 보험 종류. 건강보험, 의료급여(1종/2종), 산재보험, 자동차보험, 일반(비보험) 등으로 구분.",
      "relatedTerms": ["건강보험", "의료급여", "산재보험", "자동차보험"]
    },
    {
      "id": "T111",
      "korean": "건강보험",
      "koreanFull": "국민건강보험",
      "english": "National Health Insurance",
      "abbreviation": "NHI",
      "module": "접수",
      "primaryUser": "원무과",
      "definition": "대한민국 전 국민을 대상으로 하는 공적 의료보험. 국민건강보험공단(NHIS)이 운영.",
      "relatedTerms": ["의료급여", "NHIS", "HIRA"]
    },
    {
      "id": "T112",
      "korean": "의료급여",
      "koreanFull": "의료급여",
      "english": "Medical Aid",
      "abbreviation": null,
      "module": "접수",
      "primaryUser": "원무과",
      "definition": "저소득층 등 경제적 취약계층을 대상으로 하는 공적 의료 지원 제도. 1종(본인부담 없음/경감)과 2종으로 구분.",
      "relatedTerms": ["건강보험", "보험유형"]
    },
    {
      "id": "T113",
      "korean": "산재보험",
      "koreanFull": "산업재해보상보험",
      "english": "Industrial Accident Compensation Insurance",
      "abbreviation": null,
      "module": "접수",
      "primaryUser": "원무과",
      "definition": "업무상 재해를 당한 근로자의 치료비를 보상하는 보험. 근로복지공단에서 관리.",
      "relatedTerms": ["보험유형", "자동차보험"]
    },
    {
      "id": "T114",
      "korean": "자동차보험",
      "koreanFull": "자동차보험 / 자보차",
      "english": "Auto Insurance / Motor Vehicle Insurance",
      "abbreviation": "자보차",
      "module": "접수",
      "primaryUser": "원무과",
      "definition": "교통사고로 인한 진료비를 자동차보험에서 지급하는 유형. 별도의 수가 체계 적용.",
      "relatedTerms": ["보험유형", "산재보험"]
    },
    {
      "id": "T115",
      "korean": "본인부담상한제",
      "koreanFull": "본인부담상한제",
      "english": "Out-of-Pocket Maximum / Copayment Ceiling",
      "abbreviation": null,
      "module": "보험청구",
      "primaryUser": "원무과",
      "definition": "환자의 연간 본인부담금이 소득 수준별 상한액을 초과하면 초과분을 건강보험공단에서 부담하는 제도.",
      "relatedTerms": ["본인부담금", "건강보험"]
    },

    {
      "id": "T120",
      "korean": "수탁검사",
      "koreanFull": "수탁검사 / 위탁검사",
      "english": "Consigned Test / Outsourced Test",
      "abbreviation": null,
      "module": "수탁검사",
      "primaryUser": "의사",
      "definition": "의료기관에서 직접 시행하지 않고 외부 전문 검사기관(이원, 씨젠, 서울의과학연구소 등)에 위탁하는 검사.",
      "relatedTerms": ["검사의뢰", "검체", "LIS"]
    },
    {
      "id": "T121",
      "korean": "검사의뢰",
      "koreanFull": "검사의뢰",
      "english": "Test Order / Lab Request",
      "abbreviation": null,
      "module": "수탁검사",
      "primaryUser": "의사",
      "definition": "외부 검사기관에 검사를 요청하는 행위. EMR에서 의뢰서를 작성하여 전송.",
      "relatedTerms": ["수탁검사", "검체"]
    },
    {
      "id": "T122",
      "korean": "검체",
      "koreanFull": "검체 / 시료",
      "english": "Specimen / Sample",
      "abbreviation": null,
      "module": "수탁검사",
      "primaryUser": "간호사",
      "definition": "검사를 위해 채취한 혈액, 소변, 조직 등의 생체 시료.",
      "relatedTerms": ["검사의뢰", "채혈"]
    },
    {
      "id": "T123",
      "korean": "검사코드",
      "koreanFull": "검사코드",
      "english": "Test Code / Lab Code",
      "abbreviation": null,
      "module": "수탁검사",
      "primaryUser": "전체",
      "definition": "각 검사 항목에 부여된 고유 코드. 수탁검사 기관별로 자체 코드 체계가 있으며 EMR과 매핑하여 사용.",
      "relatedTerms": ["수탁검사", "EDI코드"]
    },
    {
      "id": "T124",
      "korean": "결과지",
      "koreanFull": "검사결과지",
      "english": "Test Result Report / Lab Report",
      "abbreviation": null,
      "module": "수탁검사",
      "primaryUser": "의사",
      "definition": "수탁검사 기관에서 검사 완료 후 보내오는 결과 보고서. EMR에 자동 연동되어 조회 가능.",
      "relatedTerms": ["수탁검사", "LIS"]
    },
    {
      "id": "T125",
      "korean": "참고치",
      "koreanFull": "참고치 / 정상범위",
      "english": "Reference Range / Normal Range",
      "abbreviation": null,
      "module": "수탁검사",
      "primaryUser": "의사",
      "definition": "검사 결과의 정상 기준 범위. 이 범위를 벗어나면 비정상(이상) 수치로 표시.",
      "relatedTerms": ["결과지", "비정상"]
    },

    {
      "id": "T130",
      "korean": "예약",
      "koreanFull": "예약",
      "english": "Appointment / Reservation",
      "abbreviation": null,
      "module": "예약",
      "primaryUser": "원무과",
      "definition": "환자가 특정 날짜/시간에 진료를 받기 위해 미리 일정을 잡는 것.",
      "relatedTerms": ["예약목록", "예약변경"]
    },
    {
      "id": "T131",
      "korean": "예약목록",
      "koreanFull": "예약목록",
      "english": "Appointment List / Schedule",
      "abbreviation": null,
      "module": "예약",
      "primaryUser": "원무과",
      "definition": "날짜별/의사별 예약된 환자 목록. 진료 스케줄 관리에 활용.",
      "relatedTerms": ["예약", "예약변경"]
    },
    {
      "id": "T132",
      "korean": "부도",
      "koreanFull": "예약부도 / 노쇼",
      "english": "No-Show",
      "abbreviation": null,
      "module": "예약",
      "primaryUser": "원무과",
      "definition": "예약한 환자가 사전 연락 없이 내원하지 않는 것. CRM 관리에서 추적.",
      "relatedTerms": ["예약", "리콜"]
    },
    {
      "id": "T133",
      "korean": "리콜",
      "koreanFull": "리콜",
      "english": "Recall / Follow-up Reminder",
      "abbreviation": null,
      "module": "CRM",
      "primaryUser": "원무과",
      "definition": "정기 검진이나 후속 진료가 필요한 환자에게 내원을 안내하는 것. 문자/전화로 알림 발송.",
      "relatedTerms": ["예약", "문자발송"]
    },
    {
      "id": "T134",
      "korean": "문자발송",
      "koreanFull": "문자발송 / SMS 발송",
      "english": "SMS / Text Message Notification",
      "abbreviation": "SMS",
      "module": "CRM",
      "primaryUser": "원무과",
      "definition": "예약 안내, 리콜, 진료 후 안내 등 환자에게 문자 메시지를 발송하는 기능.",
      "relatedTerms": ["리콜", "CRM"]
    },
    {
      "id": "T135",
      "korean": "사전문진",
      "koreanFull": "사전문진",
      "english": "Pre-Visit Questionnaire / Pre-Screening",
      "abbreviation": null,
      "module": "CRM",
      "primaryUser": "전체",
      "definition": "환자가 내원 전 모바일 등으로 미리 작성하는 문진표. 증상, 약물 알레르기, 복용약 등 사전 정보 수집.",
      "relatedTerms": ["접수", "CRM"]
    },

    {
      "id": "T140",
      "korean": "진단서",
      "koreanFull": "진단서",
      "english": "Medical Certificate / Diagnosis Certificate",
      "abbreviation": null,
      "module": "서식",
      "primaryUser": "의사",
      "definition": "의사가 환자의 질병 진단 내용을 기재하여 발급하는 공적 문서. 보험 청구, 법적 용도 등에 사용.",
      "relatedTerms": ["소견서", "제증명"]
    },
    {
      "id": "T141",
      "korean": "소견서",
      "koreanFull": "소견서",
      "english": "Medical Opinion / Medical Report",
      "abbreviation": null,
      "module": "서식",
      "primaryUser": "의사",
      "definition": "의사가 환자의 상태에 대한 의학적 소견을 기재한 문서. 진료의뢰서 등에 첨부.",
      "relatedTerms": ["진단서", "의뢰서"]
    },
    {
      "id": "T142",
      "korean": "의뢰서",
      "koreanFull": "진료의뢰서",
      "english": "Referral Letter",
      "abbreviation": null,
      "module": "서식",
      "primaryUser": "의사",
      "definition": "타 의료기관으로 환자를 의뢰할 때 작성하는 문서. 특히 상급종합병원 진료 시 필수(의료전달체계).",
      "relatedTerms": ["소견서", "회송서"]
    },
    {
      "id": "T143",
      "korean": "회송서",
      "koreanFull": "진료회송서",
      "english": "Return Referral Letter",
      "abbreviation": null,
      "module": "서식",
      "primaryUser": "의사",
      "definition": "상급 의료기관에서 치료 후 원래 의뢰한 의료기관으로 환자를 돌려보낼 때 작성하는 문서.",
      "relatedTerms": ["의뢰서", "의료전달체계"]
    },
    {
      "id": "T144",
      "korean": "제증명",
      "koreanFull": "제증명",
      "english": "Certificate Issuance / Document Issuance",
      "abbreviation": null,
      "module": "서식",
      "primaryUser": "원무과",
      "definition": "진단서, 소견서, 입퇴원확인서, 통원확인서, 진료기록사본 등 각종 의료 문서를 발급하는 업무.",
      "relatedTerms": ["진단서", "소견서", "진료기록사본"]
    },
    {
      "id": "T145",
      "korean": "진료기록사본",
      "koreanFull": "진료기록사본",
      "english": "Copy of Medical Records",
      "abbreviation": null,
      "module": "서식",
      "primaryUser": "원무과",
      "definition": "환자의 진료 기록을 복사하여 제공하는 문서. 타 의료기관 진료, 보험 청구 등에 사용.",
      "relatedTerms": ["제증명", "의무기록"]
    },
    {
      "id": "T146",
      "korean": "입퇴원확인서",
      "koreanFull": "입퇴원확인서",
      "english": "Admission/Discharge Confirmation",
      "abbreviation": null,
      "module": "서식",
      "primaryUser": "원무과",
      "definition": "환자의 입원일, 퇴원일, 진단명 등을 기재한 확인 문서.",
      "relatedTerms": ["제증명", "진단서"]
    },
    {
      "id": "T147",
      "korean": "통원확인서",
      "koreanFull": "통원확인서",
      "english": "Outpatient Visit Confirmation",
      "abbreviation": null,
      "module": "서식",
      "primaryUser": "원무과",
      "definition": "외래 진료 날짜 및 내역을 확인하는 문서. 직장 출결 확인 등에 활용.",
      "relatedTerms": ["제증명"]
    },

    {
      "id": "T150",
      "korean": "KCD",
      "koreanFull": "한국표준질병사인분류",
      "english": "Korean Standard Classification of Diseases",
      "abbreviation": "KCD",
      "module": "기초자료",
      "primaryUser": "전체",
      "definition": "WHO의 ICD-10을 기반으로 대한민국 실정에 맞게 제정한 질병 분류 체계. 현재 제8차 개정(KCD-8) 적용.",
      "relatedTerms": ["ICD-10", "상병코드"]
    },
    {
      "id": "T151",
      "korean": "ICD-10",
      "koreanFull": "국제질병분류 제10차 개정",
      "english": "International Classification of Diseases, 10th Revision",
      "abbreviation": "ICD-10",
      "module": "기초자료",
      "primaryUser": "전체",
      "definition": "세계보건기구(WHO)가 제정한 국제 표준 질병 분류 체계. KCD의 기반이 되는 국제 표준.",
      "relatedTerms": ["KCD", "상병코드"]
    },
    {
      "id": "T152",
      "korean": "상병코드",
      "koreanFull": "상병코드 / 질병코드",
      "english": "Diagnosis Code / Disease Code",
      "abbreviation": null,
      "module": "기초자료",
      "primaryUser": "전체",
      "definition": "KCD 분류에 따라 각 질병에 부여된 고유 코드. 예: J06.9(급성 상기도 감염). 보험 청구에 필수.",
      "relatedTerms": ["KCD", "주상병", "부상병"]
    },
    {
      "id": "T153",
      "korean": "EDI코드",
      "koreanFull": "EDI코드",
      "english": "EDI Code",
      "abbreviation": null,
      "module": "기초자료",
      "primaryUser": "전체",
      "definition": "건강보험심사평가원에서 행위, 약품, 치료재료에 부여한 전자 청구용 코드 체계.",
      "relatedTerms": ["행위코드", "약품코드", "EDI"]
    },
    {
      "id": "T154",
      "korean": "ATC코드",
      "koreanFull": "해부학적치료화학적분류",
      "english": "Anatomical Therapeutic Chemical Classification",
      "abbreviation": "ATC",
      "module": "기초자료",
      "primaryUser": "전체",
      "definition": "WHO에서 개발한 약물 분류 코드 체계. 약물을 해부학적 분류, 치료 분류, 화학적 분류 순으로 코드화.",
      "relatedTerms": ["약품코드", "EDI코드"]
    },
    {
      "id": "T155",
      "korean": "KOSTOM",
      "koreanFull": "한국보건의료표준용어",
      "english": "Korean Standard Terminology of Medicine",
      "abbreviation": "KOSTOM",
      "module": "기초자료",
      "primaryUser": "전체",
      "definition": "대한민국의 보건의료 분야 표준 용어 체계. 의료기관 간 정보 교류를 위한 한글/영문 표준 의학 용어집.",
      "relatedTerms": ["KCD", "SNOMED-CT"]
    },
    {
      "id": "T156",
      "korean": "약품마스터",
      "koreanFull": "약품마스터",
      "english": "Drug Master / Medication Master",
      "abbreviation": null,
      "module": "기초자료",
      "primaryUser": "전체",
      "definition": "EMR에서 사용하는 약품 기초 데이터. 약품코드, 약품명, 성분명, 규격, 약가, 용법, DUR 정보 등 포함.",
      "relatedTerms": ["약품코드", "상병마스터"]
    },
    {
      "id": "T157",
      "korean": "상병마스터",
      "koreanFull": "상병마스터",
      "english": "Diagnosis Master / Disease Master",
      "abbreviation": null,
      "module": "기초자료",
      "primaryUser": "전체",
      "definition": "EMR에서 사용하는 질병 분류 기초 데이터. KCD 코드, 한글명, 영문명, 보험 적용 여부 등 포함.",
      "relatedTerms": ["KCD", "약품마스터"]
    },
    {
      "id": "T158",
      "korean": "수가마스터",
      "koreanFull": "수가마스터",
      "english": "Fee Schedule Master",
      "abbreviation": null,
      "module": "기초자료",
      "primaryUser": "전체",
      "definition": "EMR에서 사용하는 의료 수가 기초 데이터. 행위코드, 수가명, 점수, 금액, 급여/비급여 구분 등 포함.",
      "relatedTerms": ["수가", "행위코드"]
    },
    {
      "id": "T159",
      "korean": "재료마스터",
      "koreanFull": "재료마스터",
      "english": "Material Master / Supply Master",
      "abbreviation": null,
      "module": "기초자료",
      "primaryUser": "전체",
      "definition": "치료에 사용되는 의료 재료의 기초 데이터. 재료코드, 재료명, 단가, 급여/비급여 구분 등 포함.",
      "relatedTerms": ["재료대", "수가마스터"]
    },

    {
      "id": "T160",
      "korean": "HIRA",
      "koreanFull": "건강보험심사평가원",
      "english": "Health Insurance Review & Assessment Service",
      "abbreviation": "HIRA / 심평원",
      "module": "시스템공통",
      "primaryUser": "전체",
      "definition": "보건복지부 산하 공공기관. 요양급여비용 심사, 의료서비스 평가, DUR 운영 등을 담당.",
      "relatedTerms": ["NHIS", "심사청구", "EDI"]
    },
    {
      "id": "T161",
      "korean": "NHIS",
      "koreanFull": "국민건강보험공단",
      "english": "National Health Insurance Service",
      "abbreviation": "NHIS / 공단",
      "module": "시스템공통",
      "primaryUser": "전체",
      "definition": "건강보험 가입자 관리, 보험료 징수, 보험급여 지급 등을 담당하는 공공기관.",
      "relatedTerms": ["HIRA", "건강보험"]
    },
    {
      "id": "T162",
      "korean": "요양기관",
      "koreanFull": "요양기관",
      "english": "Healthcare Provider / Medical Institution",
      "abbreviation": null,
      "module": "시스템공통",
      "primaryUser": "전체",
      "definition": "건강보험법상 의료 서비스를 제공하는 기관. 의원, 병원, 종합병원, 상급종합병원, 약국 등.",
      "relatedTerms": ["종별", "의료전달체계"]
    },
    {
      "id": "T163",
      "korean": "종별",
      "koreanFull": "종별 / 의료기관 종별",
      "english": "Institution Type / Classification",
      "abbreviation": null,
      "module": "시스템공통",
      "primaryUser": "전체",
      "definition": "의료기관의 분류. 의원(1차), 병원/종합병원(2차), 상급종합병원(3차)으로 구분. 종별에 따라 수가와 본인부담률이 다름.",
      "relatedTerms": ["요양기관", "의료전달체계"]
    },
    {
      "id": "T164",
      "korean": "의료전달체계",
      "koreanFull": "의료전달체계",
      "english": "Healthcare Delivery System / Referral System",
      "abbreviation": null,
      "module": "시스템공통",
      "primaryUser": "전체",
      "definition": "1차(의원) -> 2차(병원) -> 3차(상급종합) 단계별 진료 체계. 상급병원은 의뢰서(진료의뢰서) 지참 필요.",
      "relatedTerms": ["종별", "의뢰서"]
    },
    {
      "id": "T165",
      "korean": "진료구분",
      "koreanFull": "진료구분",
      "english": "Visit Type / Service Category",
      "abbreviation": null,
      "module": "접수",
      "primaryUser": "원무과",
      "definition": "외래/입원으로 구분. 보험 청구 시 진료 구분에 따라 청구 방식과 수가가 달라짐.",
      "relatedTerms": ["외래", "입원"]
    },
    {
      "id": "T166",
      "korean": "외래",
      "koreanFull": "외래 / 외래진료",
      "english": "Outpatient / Ambulatory Care",
      "abbreviation": "OPD",
      "module": "접수",
      "primaryUser": "전체",
      "definition": "환자가 병원에 입원하지 않고 통원하며 진료를 받는 형태.",
      "relatedTerms": ["입원", "진료구분"]
    },
    {
      "id": "T167",
      "korean": "입원",
      "koreanFull": "입원",
      "english": "Inpatient / Hospitalization",
      "abbreviation": "IPD",
      "module": "접수",
      "primaryUser": "전체",
      "definition": "환자가 병원에 입실하여 계속적인 치료와 관찰을 받는 형태.",
      "relatedTerms": ["외래", "입원료"]
    },

    {
      "id": "T170",
      "korean": "DICOM",
      "koreanFull": "의료용 디지털 영상 및 통신 표준",
      "english": "Digital Imaging and Communications in Medicine",
      "abbreviation": "DICOM",
      "module": "시스템공통",
      "primaryUser": "전체",
      "definition": "의료 영상의 저장, 전송, 출력을 위한 국제 표준 규격. PACS에서 사용.",
      "relatedTerms": ["PACS", "HL7"]
    },
    {
      "id": "T171",
      "korean": "HL7",
      "koreanFull": "보건의료정보교류 표준",
      "english": "Health Level Seven",
      "abbreviation": "HL7",
      "module": "시스템공통",
      "primaryUser": "전체",
      "definition": "의료 정보 시스템 간 데이터 교환을 위한 국제 표준 메시징 프로토콜.",
      "relatedTerms": ["FHIR", "DICOM"]
    },
    {
      "id": "T172",
      "korean": "FHIR",
      "koreanFull": "고속 의료정보교류 자원",
      "english": "Fast Healthcare Interoperability Resources",
      "abbreviation": "FHIR",
      "module": "시스템공통",
      "primaryUser": "전체",
      "definition": "HL7에서 개발한 차세대 의료 정보 교류 표준. RESTful API 기반으로 웹/모바일 환경에 적합.",
      "relatedTerms": ["HL7", "상호운용성"]
    },
    {
      "id": "T173",
      "korean": "RIS",
      "koreanFull": "영상의학정보시스템",
      "english": "Radiology Information System",
      "abbreviation": "RIS",
      "module": "시스템공통",
      "primaryUser": "전체",
      "definition": "영상의학과의 검사 예약, 접수, 판독, 결과 보고를 관리하는 시스템. PACS와 연동.",
      "relatedTerms": ["PACS", "DICOM"]
    },

    {
      "id": "T180",
      "korean": "키오스크",
      "koreanFull": "키오스크 / 무인접수기",
      "english": "Kiosk / Self Check-in Terminal",
      "abbreviation": null,
      "module": "접수",
      "primaryUser": "전체",
      "definition": "환자가 직접 접수, 수납, 제증명 발급 등을 처리할 수 있는 무인 단말기.",
      "relatedTerms": ["접수", "수납"]
    },
    {
      "id": "T181",
      "korean": "전자서명",
      "koreanFull": "전자서명",
      "english": "Electronic Signature / Digital Signature",
      "abbreviation": null,
      "module": "시스템공통",
      "primaryUser": "의사",
      "definition": "EMR에서 의사가 진료 기록이나 처방에 전자적으로 서명하여 법적 효력을 부여하는 기능.",
      "relatedTerms": ["EMR", "공인인증서"]
    },
    {
      "id": "T182",
      "korean": "의약분업",
      "koreanFull": "의약분업",
      "english": "Separation of Prescribing and Dispensing",
      "abbreviation": null,
      "module": "시스템공통",
      "primaryUser": "전체",
      "definition": "의사가 처방하고 약사가 조제하도록 역할을 분리한 제도. 2000년 시행. 원외처방의 근거.",
      "relatedTerms": ["원외처방", "처방전"]
    },
    {
      "id": "T183",
      "korean": "비대면진료",
      "koreanFull": "비대면진료 / 원격진료",
      "english": "Telemedicine / Non-Face-to-Face Consultation",
      "abbreviation": null,
      "module": "진료",
      "primaryUser": "의사",
      "definition": "화상 통화, 전화 등을 통해 환자와 의사가 직접 대면하지 않고 진료하는 방식.",
      "relatedTerms": ["진료", "EMR"]
    },

    {
      "id": "T190",
      "korean": "진료과",
      "koreanFull": "진료과 / 진료과목",
      "english": "Medical Department / Specialty",
      "abbreviation": null,
      "module": "접수",
      "primaryUser": "원무과",
      "definition": "내과, 외과, 소아과, 피부과 등 의료기관의 진료 전문 분과.",
      "relatedTerms": ["접수", "의사"]
    },
    {
      "id": "T191",
      "korean": "접수취소",
      "koreanFull": "접수취소",
      "english": "Registration Cancellation",
      "abbreviation": null,
      "module": "접수",
      "primaryUser": "원무과",
      "definition": "접수된 환자의 접수를 취소하는 처리. 환자 미내원, 오접수 등의 사유.",
      "relatedTerms": ["접수", "수납취소"]
    },
    {
      "id": "T192",
      "korean": "진료완료",
      "koreanFull": "진료완료",
      "english": "Consultation Complete",
      "abbreviation": null,
      "module": "진료",
      "primaryUser": "의사",
      "definition": "의사가 환자 진료를 마치고 차트 작성 및 처방을 완료한 상태. 이후 수납 단계로 이동.",
      "relatedTerms": ["진료", "수납"]
    },
    {
      "id": "T193",
      "korean": "사전점검",
      "koreanFull": "사전점검 / 청구사전점검",
      "english": "Pre-Claim Validation / Pre-Review Check",
      "abbreviation": null,
      "module": "보험청구",
      "primaryUser": "원무과",
      "definition": "보험 청구 전 청구 데이터의 오류 및 누락을 자동으로 점검하는 기능. 삭감을 사전 방지.",
      "relatedTerms": ["심사청구", "삭감"]
    },
    {
      "id": "T194",
      "korean": "착오청구",
      "koreanFull": "착오청구",
      "english": "Erroneous Claim / Billing Error",
      "abbreviation": null,
      "module": "보험청구",
      "primaryUser": "원무과",
      "definition": "코드 입력 오류, 상병 누락 등 실수로 인한 잘못된 보험 청구. 삭감의 주요 원인 중 하나.",
      "relatedTerms": ["삭감", "사전점검"]
    },
    {
      "id": "T195",
      "korean": "성분코드",
      "koreanFull": "성분코드",
      "english": "Ingredient Code / Active Ingredient Code",
      "abbreviation": null,
      "module": "기초자료",
      "primaryUser": "전체",
      "definition": "약품의 주성분에 부여된 코드. DUR 점검에서 병용금기, 중복 처방 확인 시 사용.",
      "relatedTerms": ["약품코드", "DUR"]
    },
    {
      "id": "T196",
      "korean": "SNOMED-CT",
      "koreanFull": "체계화된 의학용어 임상용어",
      "english": "Systematized Nomenclature of Medicine -- Clinical Terms",
      "abbreviation": "SNOMED-CT",
      "module": "기초자료",
      "primaryUser": "전체",
      "definition": "국제적으로 사용되는 체계적인 임상 의학 용어 체계. EMR의 상호운용성 확보를 위한 표준.",
      "relatedTerms": ["KOSTOM", "HL7"]
    },
    {
      "id": "T197",
      "korean": "요양기관기호",
      "koreanFull": "요양기관기호",
      "english": "Healthcare Provider ID / Institution Code",
      "abbreviation": null,
      "module": "시스템공통",
      "primaryUser": "전체",
      "definition": "건강보험심사평가원에서 각 의료기관에 부여한 고유 식별 번호. 보험 청구 시 필수 기재 항목.",
      "relatedTerms": ["요양기관", "HIRA"]
    },
    {
      "id": "T198",
      "korean": "진료실",
      "koreanFull": "진료실",
      "english": "Consultation Room / Exam Room",
      "abbreviation": null,
      "module": "진료",
      "primaryUser": "의사",
      "definition": "EMR에서 의사별/진료실별로 환자 배정 및 대기 관리를 위한 논리적 구분 단위.",
      "relatedTerms": ["진료과", "대기환자"]
    },
    {
      "id": "T199",
      "korean": "진료일",
      "koreanFull": "진료일 / 요양개시일",
      "english": "Service Date / Date of Service",
      "abbreviation": null,
      "module": "보험청구",
      "primaryUser": "원무과",
      "definition": "실제 진료가 이루어진 날짜. 보험 청구 명세서의 필수 기재 항목.",
      "relatedTerms": ["명세서", "심사청구"]
    },
    {
      "id": "T200",
      "korean": "진료비",
      "koreanFull": "진료비",
      "english": "Medical Fee / Treatment Cost",
      "abbreviation": null,
      "module": "수납",
      "primaryUser": "원무과",
      "definition": "진료에 소요된 전체 비용. 본인부담금 + 보험자부담금 + 비급여의 합계.",
      "relatedTerms": ["본인부담금", "수납"]
    }
  ],

  "summary": {
    "totalTerms": 150,
    "byModule": {
      "접수": 14,
      "진료": 23,
      "처방": 17,
      "수납": 8,
      "보험청구": 25,
      "수탁검사": 6,
      "예약": 3,
      "CRM": 3,
      "서식": 8,
      "기초자료": 12,
      "시스템공통": 16
    },
    "byPrimaryUser": {
      "전체": 51,
      "의사": 30,
      "간호사": 6,
      "원무과": 63
    },
    "sources": [
      "HIRA (건강보험심사평가원) official documentation",
      "NHIS (국민건강보험공단) official documentation",
      "UbiCare (의사랑) product documentation",
      "Korean EMR Certification Framework (EMR 전자의무기록시스템인증)",
      "KOICD (질병분류정보센터)",
      "Korean Standard Classification of Diseases (KCD)",
      "Drug Utilization Review (DUR) documentation",
      "Korean healthcare IT industry resources"
    ]
  }
}
